<?xml version="1.0" encoding="UTF-8" standalone="no"?>
<!-- Generated 2019-3-17 22:07:24 by Hibernate Tools 5.3.6.Final --><!DOCTYPE hibernate-mapping PUBLIC "-//Hibernate/Hibernate Mapping DTD 3.0//EN" "http://www.hibernate.org/dtd/hibernate-mapping-3.0.dtd">
<hibernate-mapping auto-import="true" default-access="property" default-cascade="none" default-lazy="true">
    <class catalog="tmall" dynamic-insert="false" dynamic-update="false" mutable="true" name="top.ourck.beans.User" optimistic-lock="version" polymorphism="implicit" select-before-update="false" table="user">
        <id name="id" type="java.lang.Integer">
            <column name="id"/>
            <generator class="identity"/>
        </id>
        <property generated="never" lazy="false" name="name" optimistic-lock="true" type="string" unique="false">
            <column name="name"/>
        </property>
        <property generated="never" lazy="false" name="password" optimistic-lock="true" type="string" unique="false">
            <column name="password"/>
        </property>
<!--         <set embed-xml="true" fetch="select" inverse="true" lazy="true" mutable="true" name="reviews" optimistic-lock="true" sort="unsorted" table="review">
            <key on-delete="noaction">
                <column name="uid"/>
            </key>
            <one-to-many class="top.ourck.beans.Review" embed-xml="true" not-found="exception"/>
        </set>
        <set embed-xml="true" fetch="select" inverse="true" lazy="true" mutable="true" name="orderitems" optimistic-lock="true" sort="unsorted" table="orderitem">
            <key on-delete="noaction">
                <column name="uid"/>
            </key>
            <one-to-many class="top.ourck.beans.Orderitem" embed-xml="true" not-found="exception"/>
        </set>
        <set embed-xml="true" fetch="select" inverse="true" lazy="true" mutable="true" name="orders" optimistic-lock="true" sort="unsorted" table="order_">
            <key on-delete="noaction">
                <column name="uid"/>
            </key>
            <one-to-many class="top.ourck.beans.Order" embed-xml="true" not-found="exception"/>
        </set>
 -->
     </class>
</hibernate-mapping>
